setup.cfg
setup.py
travis_runner/__init__.py
travis_runner/generate.py
travis_runner/runner.py
travis_runner.egg-info/PKG-INFO
travis_runner.egg-info/SOURCES.txt
travis_runner.egg-info/dependency_links.txt
travis_runner.egg-info/entry_points.txt
travis_runner.egg-info/requires.txt
travis_runner.egg-info/top_level.txt