Metadata-Version: 1.1
Name: travis-runner
Version: 0.6.0
Summary: Local job runner for travis using docker
Home-page: https://github.com/asmundg/travis-runner
Author: Åsmund Grammeltvedt
Author-email: asmundg@big-oil.org
License: MIT license
Platform: UNKNOWN
Classifier: Development Status :: 3 - Alpha
Classifier: Environment :: Console
Classifier: Intended Audience :: Developers
Classifier: Intended Audience :: Information Technology
Classifier: License :: OSI Approved :: MIT License
Classifier: Operating System :: POSIX
Classifier: Programming Language :: Python
Classifier: Topic :: Software Development :: Testing
